setup.py
draftcheck/__init__.py
draftcheck/rules.py
draftcheck/script.py
draftcheck/validator.py
draftcheck.egg-info/PKG-INFO
draftcheck.egg-info/SOURCES.txt
draftcheck.egg-info/dependency_links.txt
draftcheck.egg-info/entry_points.txt
draftcheck.egg-info/top_level.txt
draftcheck.egg-info/zip-safe