Metadata-Version: 1.0
Name: draftcheck
Version: 0.1
Summary: LaTeX Lint for Academic Writing
Home-page: UNKNOWN
Author: UNKNOWN
Author-email: UNKNOWN
License: UNKNOWN
Platform: UNKNOWN
